Workbook

Sheet BOOKINGS

Sheet MONTHLY REPORT
E7: from | F7: =BOOKINGS!C4
E8: to | F8: =BOOKINGS!C5
C11: COLLECTED EUR
C12: Number of transactions | F12: =COUNTIF(Transactions!D:D,"success")
C13: Total Voucher value (EUR) | F13: =SUMIF(Transactions!D:D,"success",Transactions!H:H)
C14: SUM COLLECTED | F14: =F13
C17: GRAND TOTAL COLLECTED | F17: =F14
C20: FEES - TRANSACTIONS
C21: Volume Fee | D21: ='Contract terms'!C5 | E21: =F17 | F21: =D21*E21
C22: Success tx fee | D22: =F12 | E22: ='Contract terms'!C7 | F22: =D22*E22
C23: Failed tx fee | D23: =COUNTIF(Transactions!$D:$D,"decline") | E23: ='DAILY REPORT'!N5 | F23: =D23*E23
C24: Sum Fees - Transactions | F24: =SUM(F21:F23)
C26: FEES - MONTHLY AND OTHER FEES
C27: Settlement fee Rolling Reserve | D27: ='Contract terms'!C9 | E27: 0 | F27: =D27*E27
C28: Settlement fee Current Funds | D28: ='Contract terms'!C9 | E28: 0 | F28: =D28*E28
C29: SLA Fee | F29: 0
C30: Sum Fees - Monthly and other fees | F30: =SUM(F27:F29)
C34: SUM FEES | F34: =F24+F30
C36: CHARGEBACKS AND OTHER
C37: Number of chargebacks | F37: ='Chargebacks & refunds'!C45
C38: Total Chargebacks (EUR) | F38: ='Chargebacks & refunds'!E45
C39: Chargebacks fees | D39: =F37 | E39: ='Contract terms'!C11 | F39: =D39*E39
C40: Number of refunds and corrections | F40: ='Chargebacks & refunds'!I45
C41: Total refunds and corrections (EUR) | F41: ='Chargebacks & refunds'!K45
C42: Refunds and corrections fees | D42: =F40 | E42: ='Contract terms'!C12 | F42: =D42*E42
C43: TOTAL CHARGEBACKS AND OTHER | F43: =F38+F39+F41+F42
C45: TOTALS
C46: Total Voucher Sales | F46: =F17
C47: Fees | F47: =-F34
C48: Chargebacks and other | F48: =-F43
C49: Total settlement amount | F49: =SUM(F46:F48)
C51: ='Contract terms'!B14
C52: New Rolling Reserve - transactions | D52: ='Contract terms'!C14 | F52: =D52*F17
C53: Payouts Rolling Released | F53: 0
C54: Closing Balance Rolling | F54: =SUM(F52:F53)
C57: CURRENT FUNDS
C58: Paid settle | F58: 0
C59: New Current Funds - transactions | F59: =F49-F54
C60: Settlement fee Current Funds | F60: =-F59*'Contract terms'!C10
C61: Closing Balance Current Funds | F61: =SUM(F58:F60)

Sheet DAILY REPORT
A1: TRANSACTION CURRENCY | B1: EUR
L2: FEES AND CORRECTIONS | Q2: ='Contract terms'!B14 | R2: Settlement | U2: Close Balance | W2: Close Balance Usdt
A3: DATE | B3: EURO ZONE | E3: NON-EUROZONE | H3: GRAND TOTAL
L4: VOLUME FEE | M4: SUCCESS FEE | N4: FAILED FEE | O4: CHARGEBACKS & REFUNDS | P4: CORRECTIONS | Q4: DAILY | S4: SETTLEMENT FEE RR | T4: SETTLEMENT FEE CF | V4: FX
B5: TRANSACTIONS | C5: TOTAL ACQUIRED | D5: TOTAL | E5: TRANSACTIONS | F5: TOTAL ACQUIRED | G5: TOTAL | L5: 0 | M5: ='Contract terms'!C7 | N5: 0 | Q5: ='Contract terms'!C14 | S5: ='Contract terms'!H10 | T5: 0

Sheet Chargebacks & refunds
B2: CHARGEBACKS | H2: REFUNDS

Sheet Transactions
A1: merchant name | B1: external id payment id | C1: customer name | D1: status | E1: Eurozone/Non-Eurozone | F1: transaction created at | G1: currency | H1: Amount | I1: ECB rate | J1: Adjusted ECB | K1: Amount in EUR

Sheet Sheet2

Sheet Contract terms
B2: Merchant Legal Name
B4: ECB adjustment | C4: 0
B5: Value Fee Eurozone | C5: 0
B6: Value Fee Non-Eurozone | C6: 0
B7: Success Fee | C7: 0
B8: Failed Fee | C8: 0
B9: Settlement Fee SEPA | C9: 0
B10: Settlement Fee USDT | C10: 0
B11: Chargeback Fee | C11: 0
B12: Refund Fee | C12: 0
B14: ROLLING RESERVE | C14: 0
